{
  "version": "4.0",
  "name": "Black vs 1. d4 (Slav Defense)",
  "group": "Black Repertoire",
  "color": "black",
  "description": "A solid, reliable defense to 1. d4 based on the Slav setup (c6 and d5). We keep our light-squared bishop free and build a fortress. Also covers the London System.",
  "startingMoves": "1. d4 d5",
  "tree": {
    "id": "root",
    "move": "1. d4",
    "player": "white",
    "explanation": "The Queen's Pawn Opening. White takes central control.",
    "status": "Mainline",
    "type": "Positional/Strategic",
    "children": [
      {
        "id": "d5",
        "move": "1... d5",
        "player": "black",
        "explanation": "We mirror White and contest the center! This is the most solid and classical response.",
        "status": "Mainline",
        "type": "Positional/Strategic",
        "children": [
          {
            "id": "c4_qg",
            "move": "2. c4",
            "player": "white",
            "explanation": "The Queen's Gambit. White attacks our d5 pawn. Don't worry - it's not a real gambit. Taking the pawn is fine but we'll play the Slav instead.",
            "status": "Mainline",
            "type": "Dynamic",
            "children": [
              {
                "id": "c6_slav",
                "move": "2... c6",
                "player": "black",
                "explanation": "The Slav Defense! We defend d5 with a pawn, keeping the diagonal open for our light-squared bishop. This is better than e6, which traps the bishop.",
                "status": "Mainline",
                "type": "Positional/Strategic",
                "children": [
                  {
                    "id": "nf3_slav",
                    "move": "3. Nf3",
                    "player": "white",
                    "explanation": "Natural development.",
                    "status": "Mainline",
                    "type": "Positional/Strategic",
                    "children": [
                      {
                        "id": "nf6_slav",
                        "move": "3... Nf6",
                        "player": "black",
                        "explanation": "We develop and pressure e4.",
                        "status": "Mainline",
                        "type": "Positional/Strategic",
                        "children": [
                          {
                            "id": "nc3_slav",
                            "move": "4. Nc3",
                            "player": "white",
                            "explanation": "White develops and pressures d5.",
                            "status": "Mainline",
                            "type": "Positional/Strategic",
                            "children": [
                              {
                                "id": "bf5_slav",
                                "move": "4... Bf5",
                                "player": "black",
                                "explanation": "THE KEY MOVE! We develop our bishop BEFORE playing e6. This is why we played c6 instead of e6 on move 2. Our bishop is active!",
                                "status": "Mainline",
                                "type": "Positional/Strategic",
                                "children": [
                                  {
                                    "id": "cxd5_slav",
                                    "move": "5. cxd5",
                                    "player": "white",
                                    "explanation": "White exchanges.",
                                    "status": "Mainline",
                                    "type": "Forcing",
                                    "children": [
                                      {
                                        "id": "cxd5_black",
                                        "move": "5... cxd5",
                                        "player": "black",
                                        "explanation": "We recapture. Now it's the Exchange Slav - very solid.",
                                        "status": "Mainline",
                                        "type": "Positional/Strategic",
                                        "children": [
                                          {
                                            "id": "qb3_slav",
                                            "move": "6. Qb3",
                                            "player": "white",
                                            "explanation": "White pressures b7 and d5.",
                                            "status": "Mainline",
                                            "type": "Dynamic",
                                            "children": [
                                              {
                                                "id": "qc8_slav",
                                                "move": "6... Qc8",
                                                "player": "black",
                                                "explanation": "We defend b7 and keep the bishop on f5. Solid setup.",
                                                "status": "Mainline",
                                                "type": "Defensive/Prophylactic",
                                                "children": []
                                              },
                                              {
                                                "id": "qb6_slav",
                                                "move": "6... Qb6",
                                                "player": "black",
                                                "explanation": "Offering a queen trade. If White trades, we have an easy endgame.",
                                                "status": "Mainline",
                                                "type": "Positional/Strategic",
                                                "children": []
                                              }
                                            ]
                                          },
                                          {
                                            "id": "bf4_slav",
                                            "move": "6. Bf4",
                                            "player": "white",
                                            "explanation": "White develops the bishop.",
                                            "status": "Sideline",
                                            "type": "Positional/Strategic",
                                            "children": [
                                              {
                                                "id": "e6_vs_bf4",
                                                "move": "6... e6",
                                                "player": "black",
                                                "explanation": "NOW we play e6, after the bishop is already out. Solid position.",
                                                "status": "Mainline",
                                                "type": "Positional/Strategic",
                                                "children": []
                                              }
                                            ]
                                          }
                                        ]
                                      }
                                    ]
                                  },
                                  {
                                    "id": "e3_slav",
                                    "move": "5. e3",
                                    "player": "white",
                                    "explanation": "White plays solidly.",
                                    "status": "Mainline",
                                    "type": "Positional/Strategic",
                                    "children": [
                                      {
                                        "id": "e6_main_slav",
                                        "move": "5... e6",
                                        "player": "black",
                                        "explanation": "Now we complete our development setup.",
                                        "status": "Mainline",
                                        "type": "Positional/Strategic",
                                        "children": [
                                          {
                                            "id": "bd3_slav",
                                            "move": "6. Bd3",
                                            "player": "white",
                                            "explanation": "White develops.",
                                            "status": "Mainline",
                                            "type": "Positional/Strategic",
                                            "children": [
                                              {
                                                "id": "bxd3_trade",
                                                "move": "6... Bxd3",
                                                "player": "black",
                                                "explanation": "We can trade bishops, simplifying. Or we can retreat with Bg6.",
                                                "status": "Mainline",
                                                "type": "Positional/Strategic",
                                                "children": [
                                                  {
                                                    "id": "qxd3",
                                                    "move": "7. Qxd3",
                                                    "player": "white",
                                                    "explanation": "White recaptures.",
                                                    "status": "Mainline",
                                                    "type": "Positional/Strategic",
                                                    "children": [
                                                      {
                                                        "id": "nbd7_slav",
                                                        "move": "7... Nbd7",
                                                        "player": "black",
                                                        "explanation": "We develop. A typical Slav middlegame position.",
                                                        "status": "Mainline",
                                                        "type": "Positional/Strategic",
                                                        "children": []
                                                      }
                                                    ]
                                                  }
                                                ]
                                              }
                                            ]
                                          }
                                        ]
                                      }
                                    ]
                                  }
                                ]
                              },
                              {
                                "id": "e6_qgd",
                                "move": "4... e6",
                                "player": "black",
                                "explanation": "Transposes to the Semi-Slav. Also playable but the bishop is locked in.",
                                "status": "Sideline",
                                "type": "Positional/Strategic",
                                "children": []
                              }
                            ]
                          },
                          {
                            "id": "e3_slow",
                            "move": "4. e3",
                            "player": "white",
                            "explanation": "White plays solidly, often heading for a Colle System.",
                            "status": "Sideline",
                            "type": "Positional/Strategic",
                            "children": [
                              {
                                "id": "bf5_vs_e3",
                                "move": "4... Bf5",
                                "player": "black",
                                "explanation": "Same idea - get the bishop out!",
                                "status": "Mainline",
                                "type": "Positional/Strategic",
                                "children": []
                              }
                            ]
                          }
                        ]
                      }
                    ]
                  },
                  {
                    "id": "nc3_slav",
                    "move": "3. Nc3",
                    "player": "white",
                    "explanation": "White develops the knight first.",
                    "status": "Mainline",
                    "type": "Positional/Strategic",
                    "children": [
                      {
                        "id": "nf6_vs_nc3",
                        "move": "3... Nf6",
                        "player": "black",
                        "explanation": "Natural development.",
                        "status": "Mainline",
                        "type": "Positional/Strategic",
                        "children": [
                          {
                            "id": "nf3_transpose",
                            "move": "4. Nf3",
                            "player": "white",
                            "explanation": "Transposes to main lines.",
                            "status": "Mainline",
                            "type": "Positional/Strategic",
                            "children": [
                              {
                                "id": "bf5_transpose",
                                "move": "4... Bf5",
                                "player": "black",
                                "explanation": "Same setup as before.",
                                "status": "Mainline",
                                "type": "Positional/Strategic",
                                "children": []
                              }
                            ]
                          }
                        ]
                      }
                    ]
                  },
                  {
                    "id": "cxd5_exchange",
                    "move": "3. cxd5",
                    "player": "white",
                    "explanation": "The Exchange Variation. White simplifies early.",
                    "status": "Sideline",
                    "type": "Positional/Strategic",
                    "children": [
                      {
                        "id": "cxd5_exchange_black",
                        "move": "3... cxd5",
                        "player": "black",
                        "explanation": "We recapture. Symmetrical pawn structure leads to equal play.",
                        "status": "Mainline",
                        "type": "Positional/Strategic",
                        "children": [
                          {
                            "id": "nc3_exchange",
                            "move": "4. Nc3",
                            "player": "white",
                            "explanation": "White develops.",
                            "status": "Mainline",
                            "type": "Positional/Strategic",
                            "children": [
                              {
                                "id": "nf6_exchange",
                                "move": "4... Nf6",
                                "player": "black",
                                "explanation": "We develop. Equal position.",
                                "status": "Mainline",
                                "type": "Positional/Strategic",
                                "children": [
                                  {
                                    "id": "bf4_exchange",
                                    "move": "5. Bf4",
                                    "player": "white",
                                    "explanation": "White develops the bishop.",
                                    "status": "Mainline",
                                    "type": "Positional/Strategic",
                                    "children": [
                                      {
                                        "id": "bf5_exchange",
                                        "move": "5... Bf5",
                                        "player": "black",
                                        "explanation": "We mirror. The position is completely equal.",
                                        "status": "Mainline",
                                        "type": "Positional/Strategic",
                                        "children": []
                                      }
                                    ]
                                  }
                                ]
                              }
                            ]
                          }
                        ]
                      }
                    ]
                  }
                ]
              },
              {
                "id": "e6_qgd",
                "move": "2... e6",
                "player": "black",
                "explanation": "The Queen's Gambit Declined. Also very solid but the bishop gets locked behind the pawns.",
                "status": "Sideline",
                "type": "Positional/Strategic",
                "children": []
              }
            ]
          },
          {
            "id": "bf4_london",
            "move": "2. Bf4",
            "player": "white",
            "explanation": "The London System. White develops the bishop before e3. Very popular at club level.",
            "status": "Mainline",
            "type": "Positional/Strategic",
            "children": [
              {
                "id": "c5_vs_london",
                "move": "2... c5",
                "player": "black",
                "explanation": "We immediately challenge the center! This is the most active response to the London.",
                "status": "Mainline",
                "type": "Dynamic",
                "children": [
                  {
                    "id": "e3_london",
                    "move": "3. e3",
                    "player": "white",
                    "explanation": "White plays their standard setup.",
                    "status": "Mainline",
                    "type": "Positional/Strategic",
                    "children": [
                      {
                        "id": "nc6_vs_london",
                        "move": "3... Nc6",
                        "player": "black",
                        "explanation": "We develop and pressure d4.",
                        "status": "Mainline",
                        "type": "Positional/Strategic",
                        "children": [
                          {
                            "id": "c3_london",
                            "move": "4. c3",
                            "player": "white",
                            "explanation": "White reinforces d4.",
                            "status": "Mainline",
                            "type": "Positional/Strategic",
                            "children": [
                              {
                                "id": "qb6_london",
                                "move": "4... Qb6",
                                "player": "black",
                                "explanation": "We attack b2 and d4! This is the critical test of the London. White must defend accurately.",
                                "status": "Mainline",
                                "type": "Dynamic",
                                "children": [
                                  {
                                    "id": "qb3_london",
                                    "move": "5. Qb3",
                                    "player": "white",
                                    "explanation": "White offers a queen trade.",
                                    "status": "Mainline",
                                    "type": "Positional/Strategic",
                                    "children": [
                                      {
                                        "id": "qxb3_trade",
                                        "move": "5... Qxb3",
                                        "player": "black",
                                        "explanation": "We can trade and get an equal endgame.",
                                        "status": "Mainline",
                                        "type": "Positional/Strategic",
                                        "children": [
                                          {
                                            "id": "axb3",
                                            "move": "6. axb3",
                                            "player": "white",
                                            "explanation": "White recaptures. Equal game.",
                                            "status": "Mainline",
                                            "type": "Positional/Strategic",
                                            "children": []
                                          }
                                        ]
                                      },
                                      {
                                        "id": "c4_tension",
                                        "move": "5... c4",
                                        "player": "black",
                                        "explanation": "We push and gain space, though the pawn can become a target.",
                                        "status": "Sideline",
                                        "type": "Dynamic",
                                        "children": []
                                      }
                                    ]
                                  },
                                  {
                                    "id": "qc1_passive",
                                    "move": "5. Qc1",
                                    "player": "white",
                                    "explanation": "A passive retreat. We're already doing well.",
                                    "status": "Sideline",
                                    "type": "Defensive/Prophylactic",
                                    "children": [
                                      {
                                        "id": "bf5_london",
                                        "move": "5... Bf5",
                                        "player": "black",
                                        "explanation": "We develop actively. Black is very comfortable.",
                                        "status": "Mainline",
                                        "type": "Positional/Strategic",
                                        "children": []
                                      }
                                    ]
                                  }
                                ]
                              },
                              {
                                "id": "nf6_vs_c3",
                                "move": "4... Nf6",
                                "player": "black",
                                "explanation": "Simple development also works well.",
                                "status": "Mainline",
                                "type": "Positional/Strategic",
                                "children": []
                              }
                            ]
                          }
                        ]
                      }
                    ]
                  }
                ]
              },
              {
                "id": "nf6_vs_london",
                "move": "2... Nf6",
                "player": "black",
                "explanation": "Also good - simple development.",
                "status": "Mainline",
                "type": "Positional/Strategic",
                "children": [
                  {
                    "id": "e3_london2",
                    "move": "3. e3",
                    "player": "white",
                    "explanation": "Standard London.",
                    "status": "Mainline",
                    "type": "Positional/Strategic",
                    "children": [
                      {
                        "id": "c5_london2",
                        "move": "3... c5",
                        "player": "black",
                        "explanation": "We challenge the center as usual.",
                        "status": "Mainline",
                        "type": "Dynamic",
                        "children": []
                      },
                      {
                        "id": "bf5_london2",
                        "move": "3... Bf5",
                        "player": "black",
                        "explanation": "Mirroring White! This leads to symmetrical but playable positions.",
                        "status": "Sideline",
                        "type": "Positional/Strategic",
                        "children": []
                      }
                    ]
                  }
                ]
              }
            ]
          },
          {
            "id": "nf3_standard",
            "move": "2. Nf3",
            "player": "white",
            "explanation": "Flexible - White might play c4 next (Queen's Gambit) or Bf4 (London).",
            "status": "Mainline",
            "type": "Positional/Strategic",
            "children": [
              {
                "id": "nf6_vs_nf3",
                "move": "2... Nf6",
                "player": "black",
                "explanation": "We develop and wait to see White's plan.",
                "status": "Mainline",
                "type": "Positional/Strategic",
                "children": [
                  {
                    "id": "c4_qg_transpose",
                    "move": "3. c4",
                    "player": "white",
                    "explanation": "Now it's the Queen's Gambit.",
                    "status": "Mainline",
                    "type": "Positional/Strategic",
                    "children": [
                      {
                        "id": "c6_transpose",
                        "move": "3... c6",
                        "player": "black",
                        "explanation": "Back to our Slav!",
                        "status": "Mainline",
                        "type": "Positional/Strategic",
                        "children": []
                      }
                    ]
                  },
                  {
                    "id": "bf4_transpose",
                    "move": "3. Bf4",
                    "player": "white",
                    "explanation": "The London System.",
                    "status": "Mainline",
                    "type": "Positional/Strategic",
                    "children": [
                      {
                        "id": "c5_transpose",
                        "move": "3... c5",
                        "player": "black",
                        "explanation": "We challenge the center.",
                        "status": "Mainline",
                        "type": "Dynamic",
                        "children": []
                      }
                    ]
                  }
                ]
              }
            ]
          }
        ]
      },
      {
        "id": "nf6_vs_d4",
        "move": "1... Nf6",
        "player": "black",
        "explanation": "The Indian Defense setup. Keeps options open - can go to King's Indian, Nimzo, etc.",
        "status": "Sideline",
        "type": "Positional/Strategic",
        "children": [
          {
            "id": "c4_after_nf6",
            "move": "2. c4",
            "player": "white",
            "explanation": "White grabs space.",
            "status": "Mainline",
            "type": "Positional/Strategic",
            "children": [
              {
                "id": "e6_nimzo",
                "move": "2... e6",
                "player": "black",
                "explanation": "Preparing ...Bb4 (Nimzo-Indian) or ...d5 (QGD structure).",
                "status": "Mainline",
                "type": "Positional/Strategic",
                "children": [
                  {
                    "id": "nc3_nimzo",
                    "move": "3. Nc3",
                    "player": "white",
                    "explanation": "White develops.",
                    "status": "Mainline",
                    "type": "Positional/Strategic",
                    "children": [
                      {
                        "id": "bb4_nimzo",
                        "move": "3... Bb4",
                        "player": "black",
                        "explanation": "The Nimzo-Indian! We pin the knight and control e4.",
                        "status": "Mainline",
                        "type": "Dynamic",
                        "children": []
                      },
                      {
                        "id": "d5_qgd",
                        "move": "3... d5",
                        "player": "black",
                        "explanation": "We can also transpose to QGD structures.",
                        "status": "Mainline",
                        "type": "Positional/Strategic",
                        "children": []
                      }
                    ]
                  }
                ]
              }
            ]
          },
          {
            "id": "bf4_after_nf6",
            "move": "2. Bf4",
            "player": "white",
            "explanation": "London System.",
            "status": "Mainline",
            "type": "Positional/Strategic",
            "children": [
              {
                "id": "d5_vs_london_nf6",
                "move": "2... d5",
                "player": "black",
                "explanation": "We can go back to our d5/c5 setup.",
                "status": "Mainline",
                "type": "Positional/Strategic",
                "children": []
              }
            ]
          }
        ]
      }
    ]
  }
}
